MANIFEST.in
README.md
setup.cfg
setup.py
versioneer.py
bin/mkauthlist
mkauthlist/__init__.py
mkauthlist/_version.py
mkauthlist/mkauthlist.py
mkauthlist/tmp-mkauthlist.py
mkauthlist.egg-info/PKG-INFO
mkauthlist.egg-info/SOURCES.txt
mkauthlist.egg-info/dependency_links.txt
mkauthlist.egg-info/requires.txt
mkauthlist.egg-info/top_level.txt