Metadata-Version: 1.1
Name: mkauthlist
Version: 1.3.0
Summary: Set of simple tools for working in DES.
Home-page: https://github.com/kadrlica/mkauthlist
Author: Alex Drlica-Wagner
Author-email: kadrlica@fnal.gov
License: MIT
Keywords: latex des
Platform: any
Classifier: Programming Language :: Python
Classifier: Development Status :: 4 - Beta
Classifier: Natural Language :: English
Classifier: Intended Audience :: Science/Research
